adafruit_usb_host_descriptors.py
adafruit_circuitpython_usb_host_descriptors-0.5.0.dist-info/licenses/LICENSE
adafruit_circuitpython_usb_host_descriptors-0.5.0.dist-info/METADATA
adafruit_circuitpython_usb_host_descriptors-0.5.0.dist-info/WHEEL
adafruit_circuitpython_usb_host_descriptors-0.5.0.dist-info/top_level.txt
adafruit_circuitpython_usb_host_descriptors-0.5.0.dist-info/RECORD
