Metadata-Version: 2.4
Name: adafruit-circuitpython-usb-host-descriptors
Version: 0.5.0
Summary: Helpers for getting USB descriptors
Author-email: Adafruit Industries <circuitpython@adafruit.com>
License: MIT
Project-URL: Homepage, https://github.com/adafruit/Adafruit_CircuitPython_USB_Host_Descriptors
Keywords: adafruit,blinka,circuitpython,micropython,usb-host-descriptors,usb
Classifier: Intended Audience :: Developers
Classifier: Topic :: Software Development :: Libraries
Classifier: Topic :: Software Development :: Embedded Systems
Classifier: Topic :: System :: Hardware
Classifier: License :: OSI Approved :: MIT License
Classifier: Programming Language :: Python :: 3
License-File: LICENSE
Requires-Dist: Adafruit-Blinka
Provides-Extra: optional
Dynamic: license-file
